Vivado/Full_adder/full_adder.v
module full_adder (
    A1, A2, Cin, S,Cout
);
    input A1, A2, Cin;
    output S,Cout;

    reg [1:0] temp;
    always @(*) begin
        temp = {1'b0,A1} + {1'b0,A2}+{1'b0,Cin};
    end
    assign S = temp[0];
    assign Cout = temp[1];
    
endmodule

Vivado/Full_adder/full_adder_tb.v
`timescale 1ns/1ps
`include "full_adder.v"
module full_adder_tb;

reg A1,A2,Cin;
wire S,Cout;

// full_adder(
//     .a1(A1),
//     .a2(A2);
//     .cin(Cin);
//     .s(S);
//     .cout(Cout);
//     );

full_adder uut (A1,A2,Cin,S,Cout);

initial begin
    $dumpfile("full_adder_tb.vcd");
    $dumpvars(0,full_adder_tb);

    A1 = 0 ;
    A2 = 0 ;
    Cin = 0 ;
    #5;

    A1 = 0 ;
    A2 = 0 ;
    Cin = 1 ;
    #5;

    A1 = 0 ;
    A2 = 1 ;
    Cin = 0 ;
    #5;

    A1 = 0 ;
    A2 = 1 ;
    Cin = 1 ;
    #5;

    A1 = 1 ;
    A2 = 0 ;
    Cin = 0 ;
    #5;

    A1 = 1 ;
    A2 = 0 ;
    Cin = 1 ;
    #5;

    A1 = 1 ;
    A2 = 1 ;
    Cin = 0 ;
    #5;

    A1 = 1 ;
    A2 = 1 ;
    Cin = 1 ;
    #5;

end

endmodule

Vivado/Full_adder/full_adder_tb.vcd
$date
	Thu Jun 02 12:39:07 2022
$end
$version
	Icarus Verilog
$end
$timescale
	1ps
$end
$scope module full_adder_tb $end
$var wire 1 ! S $end
$var wire 1 " Cout $end
$var reg 1 # A1 $end
$var reg 1 $ A2 $end
$var reg 1 % Cin $end
$scope module uut $end
$var wire 1 # A1 $end
$var wire 1 $ A2 $end
$var wire 1 % Cin $end
$var wire 1 ! S $end
$var wire 1 " Cout $end
$var reg 2 & temp [1:0] $end
$upscope $end
$upscope $end
$enddefinitions $end
#0
$dumpvars
b0 &
0%
0$
0#
0"
0!
$end
#5000
1!
b1 &
1%
#10000
0%
1$
#15000
0!
1"
b10 &
1%
#20000
1!
0"
b1 &
0%
0$
1#
#25000
0!
1"
b10 &
1%
#30000
0%
1$
#35000
1!
b11 &
1%
